{
  "formatVersion": 1,
  "database": {
    "version": 1,
    "identityHash": "3da4216a1ce32a6a9d127933e616483c",
    "entities": [
      {
        "tableName": "alignment_events",
        "createSql": "CREATE TABLE IF NOT EXISTS `${TABLE_NAME}` (`id` INTEGER PRIMARY KEY AUTOINCREMENT NOT NULL, `timestamp` INTEGER NOT NULL, `eventType` TEXT NOT NULL, `isManualEntry` INTEGER NOT NULL, `notes` TEXT)",
        "fields": [
          {
            "fieldPath": "id",
            "columnName": "id",
            "affinity": "INTEGER",
            "notNull": true
          },
          {
            "fieldPath": "timestamp",
            "columnName": "timestamp",
            "affinity": "INTEGER",
            "notNull": true
          },
          {
            "fieldPath": "eventType",
            "columnName": "eventType",
            "affinity": "TEXT",
            "notNull": true
          },
          {
            "fieldPath": "isManualEntry",
            "columnName": "isManualEntry",
            "affinity": "INTEGER",
            "notNull": true
          },
          {
            "fieldPath": "notes",
            "columnName": "notes",
            "affinity": "TEXT",
            "notNull": false
          }
        ],
        "primaryKey": {
          "autoGenerate": true,
          "columnNames": [
            "id"
          ]
        },
        "indices": [],
        "foreignKeys": []
      }
    ],
    "views": [],
    "setupQueries": [
      "CREATE TABLE IF NOT EXISTS room_master_table (id INTEGER PRIMARY KEY,identity_hash TEXT)",
      "INSERT OR REPLACE INTO room_master_table (id,identity_hash) VALUES(42, '3da4216a1ce32a6a9d127933e616483c')"
    ]
  }
}